{"GlobalPropertiesHash":"2ilJ2M8+ZdH0swl4cXFj9Ji8kay0R08ISE/fEc+OL0o=","FingerprintPatternsHash":"8ZRc1sGeVrPBx4lD717BgRaQekyh78QKV9SKsdt638U=","PropertyOverridesHash":"8ZRc1sGeVrPBx4lD717BgRaQekyh78QKV9SKsdt638U=","InputHashes":["hgozSa2H\u002Bp\u002Bt0FlsilLELbzum5\u002BX9354VGYMT7KmxHM="],"CachedAssets":{"hgozSa2H\u002Bp\u002Bt0FlsilLELbzum5\u002BX9354VGYMT7KmxHM=":{"Identity":"C:\\Users\\franc\\repos\\backend-net\\obj\\Debug\\net9.0\\compressed\\z9ugkzmvuz-pwg9sk7qmm.gz","SourceId":"backend","SourceType":"Discovered","ContentRoot":"C:\\Users\\franc\\repos\\backend-net\\obj\\Debug\\net9.0\\compressed\\","BasePath":"_content/backend","RelativePath":"data/portfolio#[.{fingerprint=pwg9sk7qmm}]?.json.gz","AssetKind":"All","AssetMode":"All","AssetRole":"Alternative","AssetMergeBehavior":null,"AssetMergeSource":"","RelatedAsset":"C:\\Users\\franc\\repos\\backend-net\\wwwroot\\data\\portfolio.json","AssetTraitName":"Content-Encoding","AssetTraitValue":"gzip","Fingerprint":"g2u8uq3tb1","Integrity":"yL\u002BaWKc6CBXB3ucWUQLbLG8AX/vvggPUOcXnljt6OJA=","CopyToOutputDirectory":"Never","CopyToPublishDirectory":"PreserveNewest","OriginalItemSpec":"C:\\Users\\franc\\repos\\backend-net\\wwwroot\\data\\portfolio.json","FileLength":1166,"LastWriteTime":"2025-05-23T00:08:06.3897558+00:00"}},"CachedCopyCandidates":{}}